splitter_cell/__init__.py
splitter_cell/main.py
splitter_cell-0.0.5.dist-info/METADATA
splitter_cell-0.0.5.dist-info/WHEEL
splitter_cell-0.0.5.dist-info/entry_points.txt
splitter_cell-0.0.5.dist-info/top_level.txt
splitter_cell-0.0.5.dist-info/RECORD
