Metadata-Version: 2.1
Name: splitter-cell
Version: 0.0.5
Summary: A tool to split files and combine them together again using the command-line.
Home-page: UNKNOWN
Author: Kevin Hill
Author-email: kah.kevin.hill@gmail.com
License: BSD
Keywords: split any file
Platform: UNKNOWN
Classifier: Development Status :: 3 - Alpha
Classifier: Topic :: Utilities
Classifier: License :: OSI Approved :: BSD License
Requires-Dist: baranomi
Requires-Dist: patman
Requires-Dist: click
Requires-Dist: m3u8
